ff/__init__.py
ff/__main__.py
ff/cli.py
ff/config.py
ff/pattern.py
ff/plugin.py
ff/scanner.py
ff/utils.py
ff_find-1.0.5.dist-info/DESCRIPTION.rst
ff_find-1.0.5.dist-info/entry_points.txt
ff_find-1.0.5.dist-info/METADATA
ff_find-1.0.5.dist-info/metadata.json
ff_find-1.0.5.dist-info/RECORD
ff_find-1.0.5.dist-info/top_level.txt
ff_find-1.0.5.dist-info/WHEEL
ff_plugins/__init__.py
ff_plugins/ffplugin_test_size.py
