Metadata-Version: 2.0
Name: ff-find
Version: 1.0.5
Summary: Easily search and process files by names.
Home-page: http://mysz.github.io/ff/
Author: Marcin Sztolcman
Author-email: marcin@urzenia.net
License: MIT
Keywords: search,find,filesystem,files,directories
Platform: UNKNOWN
Classifier: Development Status :: 5 - Production/Stable
Classifier: Intended Audience :: Developers
Classifier: Intended Audience :: System Administrators
Classifier: Environment :: Console
Classifier: License :: OSI Approved :: MIT License
Classifier: Operating System :: OS Independent
Classifier: Programming Language :: Python
Classifier: Programming Language :: Python :: 2
Classifier: Programming Language :: Python :: 2.7
Classifier: Programming Language :: Python :: 3
Classifier: Programming Language :: Python :: 3.3
Classifier: Programming Language :: Python :: 3.4
Classifier: Topic :: Utilities
Classifier: Topic :: Software Development
Classifier: Topic :: System
Requires-Dist: argparse
Requires-Dist: tmcolors (==0.1.1)
